concord/__init__.py
concord/bm.py
concord/concord.py
concord/ml.py
concord/pl.py
concord/sm.py
concord/ul.py
concord/benchmarking/__init__.py
concord/benchmarking/benchmark.py
concord/benchmarking/geometry.py
concord/benchmarking/knn_probe.py
concord/benchmarking/linear_probe.py
concord/benchmarking/pipeline_dim_reduction.py
concord/benchmarking/pipeline_integration.py
concord/benchmarking/tda.py
concord/benchmarking/time_memory.py
concord/model/__init__.py
concord/model/anndataset.py
concord/model/augment.py
concord/model/build_layer.py
concord/model/chunkloader.py
concord/model/dataloader.py
concord/model/knn.py
concord/model/loss.py
concord/model/model.py
concord/model/sampler.py
concord/model/trainer.py
concord/plotting/__init__.py
concord/plotting/palettes.py
concord/plotting/pl_batch.py
concord/plotting/pl_benchmark.py
concord/plotting/pl_datacoverage.py
concord/plotting/pl_embedding.py
concord/plotting/pl_enrichment.py
concord/plotting/pl_general.py
concord/plotting/pl_geometry.py
concord/plotting/pl_graph.py
concord/plotting/pl_heatmap.py
concord/plotting/pl_model.py
concord/plotting/pl_path.py
concord/plotting/pl_tda.py
concord/simulation/__init__.py
concord/simulation/advanced_helper.py
concord/simulation/simulation.py
concord/utils/Hs_Mm_conversion.py
concord/utils/__init__.py
concord/utils/anndata_utils.py
concord/utils/batch_analysis.py
concord/utils/cell_cycle.py
concord/utils/coverage_estimator.py
concord/utils/dim_reduction.py
concord/utils/doublet_utils.py
concord/utils/enrichment_analysis.py
concord/utils/estimate_dropout_rate.py
concord/utils/feature_selector.py
concord/utils/importance_analysis.py
concord/utils/integration_methods.py
concord/utils/io.py
concord/utils/other_util.py
concord/utils/path_analysis.py
concord/utils/value_check.py
concord/utils/visCello.py
concord_sc-1.0.13.dist-info/licenses/LICENSE.md
concord_sc-1.0.13.dist-info/METADATA
concord_sc-1.0.13.dist-info/WHEEL
concord_sc-1.0.13.dist-info/top_level.txt
concord_sc-1.0.13.dist-info/RECORD
